solys2/__init__.py
solys2/common.py
solys2/connection.py
solys2/response.py
solys2/solys2.py
solys2/automation/__init__.py
solys2/automation/autohelper.py
solys2/automation/autotrack.py
solys2/automation/calibration.py
solys2/automation/positioncalc.py
solys2-0.2.6.dist-info/LICENSE
solys2-0.2.6.dist-info/METADATA
solys2-0.2.6.dist-info/WHEEL
solys2-0.2.6.dist-info/top_level.txt
solys2-0.2.6.dist-info/RECORD
