Metadata-Version: 2.1
Name: solys2
Version: 0.2.6
Summary: Solys2 interface and automatic tracking functions.
Home-page: https://github.com/GOA-UVa/solys2
Author: Group of Atmospheric Optics (GOA-UVa), Universidad de Valladolid
Author-email: gaton@goa.uva.es
License: GPLv3
Project-URL: Bug Tracker, https://github.com/GOA-UVa/solys2/issues
Classifier: Programming Language :: Python :: 3
Classifier: Operating System :: OS Independent
Classifier: License :: OSI Approved :: GNU General Public License v3 (GPLv3)
Requires-Python: >=3.7
License-File: LICENSE
Requires-Dist: numpy (>=1.21.5)
Requires-Dist: pylunar (>=0.6.0)
Requires-Dist: pysolar (>=0.10)
Requires-Dist: ephem (>=4.1.3)
Requires-Dist: spicedmoon (>=1.0.1)
Requires-Dist: spicedsun (>=0.0.2)
